setup.py
umdh/__init__.py
umdh/umdh.py
umdh.egg-info/PKG-INFO
umdh.egg-info/SOURCES.txt
umdh.egg-info/dependency_links.txt
umdh.egg-info/not-zip-safe
umdh.egg-info/requires.txt
umdh.egg-info/top_level.txt