Metadata-Version: 1.0
Name: umdh
Version: 0.3
Summary: Tools for working with University of Michigan dining hall data
Home-page: http://github.com/davidwilemski/umdh
Author: David Wilemski
Author-email: david@davidwilemski.com
License: ISC
Platform: UNKNOWN
